<system>
  <distance errorplus="0.19" errorminus="-0.2">18.15</distance>
  <name>14 Her</name>
  <declination>43 49 03</declination>
  <star>
    <radius/>
    <temperature errorplus="87.0" errorminus="-87.0">5311.0</temperature>
    <name>14 Her</name>
    <mass errorplus="0.05" errorminus="-0.05">0.9</mass>
    <planet>
      <radius/>
      <semimajoraxis errorplus="0.05" errorminus="-0.05">2.77</semimajoraxis>
      <lastupdate>2014-05-14</lastupdate>
      <eccentricity>0.369</eccentricity>
      <name>14 Her b</name>
      <inclination/>
      <discoverymethod>RV</discoverymethod>
      <period errorplus="2.5" errorminus="-2.5">1773.4</period>
    </planet>
  </star>
  <rightascension>16 36 04</rightascension>
</system>

