<system>
  <name>BD+15 2375</name>
  <rightascension>11 28 55</rightascension>
  <star>
    <name>BD+15 2375</name>
    <radius errorplus="1.45" errorminus="-1.45">8.95</radius>
    <mass errorplus="0.14" errorminus="-0.14">1.08</mass>
    <temperature errorplus="30.0" errorminus="-30.0">4649.0</temperature>
    <planet>
      <name>BD+15 2375 b</name>
      <discoverymethod>RV</discoverymethod>
      <lastupdate>2016-02-04</lastupdate>
      <radius errorplus="1.45" errorminus="-1.45">8.95</radius>
      <semimajoraxis errorplus="0.027" errorminus="-0.027">0.576</semimajoraxis>
      <eccentricity>0.001</eccentricity>
      <period errorplus="0.4" errorminus="-0.4">153.2</period>
      <inclination/>
    </planet>
  </star>
  <distance errorplus="165.0" errorminus="-165.0">774.0</distance>
  <declination>14 36 58</declination>
</system>

