<system><rightascension>06 11 40</rightascension><star><mass errorminus="-0.02" errorplus="0.03">1.16</mass><planet><inclination errorminus="-0.085" errorplus="0.0">90.0</inclination><period errorminus="-0.0" errorplus="0.0">9.2</period><radius errorminus="-0.03" errorplus="0.01">1.17</radius><discoverymethod>transit</discoverymethod><semimajoraxis errorminus="-0.001" errorplus="0.001">0.09</semimajoraxis><lastupdate>2014-05-14</lastupdate><name>CoRoT-4 b</name><eccentricity>0.0</eccentricity></planet><name>CoRoT-4</name><radius errorminus="-0.03" errorplus="0.01">1.17</radius><temperature errorminus="-60.0" errorplus="60.0">6190.0</temperature></star><distance></distance><name>CoRoT-4</name><declination>00 40 21</declination></system>
