<system>
  <rightascension>23 43 27</rightascension>
  <distance>169.78</distance>
  <name>HD 219415</name>
  <star>
    <temperature errorminus="-20.0" errorplus="20.0">4820.0</temperature>
    <mass errorminus="-0.1" errorplus="0.1">1.0</mass>
    <name>HD 219415</name>
    <planet>
      <eccentricity>0.4</eccentricity>
      <period errorminus="-32.7" errorplus="32.7">2093.3</period>
      <radius errorminus="-0.4" errorplus="0.4">2.9</radius>
      <discoverymethod>RV</discoverymethod>
      <inclination/>
      <name>HD 219415 b</name>
      <lastupdate>2015-09-18</lastupdate>
      <semimajoraxis>3.2</semimajoraxis>
    </planet>
    <radius errorminus="-0.4" errorplus="0.4">2.9</radius>
  </star>
  <declination>56 43 49</declination>
</system>

