<system>
  <name>HD 4203</name>
  <star>
    <radius/>
    <name>HD 4203</name>
    <temperature>5702.0</temperature>
    <planet>
      <radius/>
      <semimajoraxis errorplus="0.0222" errorminus="-0.0222">1.1735</semimajoraxis>
      <eccentricity>0.52</eccentricity>
      <discoverymethod>RV</discoverymethod>
      <name>HD 4203 b</name>
      <lastupdate>2014-05-14</lastupdate>
      <period errorplus="0.3" errorminus="-0.3">437.1</period>
      <inclination/>
    </planet>
    <planet>
      <radius/>
      <semimajoraxis errorplus="1.93" errorminus="-0.56">6.95</semimajoraxis>
      <eccentricity>0.24</eccentricity>
      <discoverymethod>RV</discoverymethod>
      <name>HD 4203 c</name>
      <lastupdate>2014-05-14</lastupdate>
      <period errorplus="4500.0" errorminus="-4500.0">6700.0</period>
      <inclination/>
    </planet>
    <mass>1.13</mass>
  </star>
  <distance errorplus="7.0" errorminus="-8.53">77.82</distance>
  <declination>20 26 56</declination>
  <rightascension>00 10 18</rightascension>
</system>

