<system>
  <name>HIP 57050</name>
  <rightascension>11 26 09</rightascension>
  <star>
    <name>HIP 57050</name>
    <radius/>
    <mass/>
    <temperature/>
    <planet>
      <name>HIP 57050 b</name>
      <discoverymethod>RV</discoverymethod>
      <lastupdate>2014-05-14</lastupdate>
      <radius/>
      <semimajoraxis errorplus="4.2e-05" errorminus="-4.2e-05">0.163506</semimajoraxis>
      <eccentricity>0.314</eccentricity>
      <period errorplus="0.0" errorminus="-0.0">41.4</period>
      <inclination/>
    </planet>
  </star>
  <distance errorplus="0.36" errorminus="-0.38">11.03</distance>
  <declination>42 45 07</declination>
</system>

