<system>
  <name>K2-6</name>
  <star>
    <radius errorplus="0.14" errorminus="-0.09">0.96</radius>
    <name>K2-6</name>
    <temperature errorplus="79.0" errorminus="-98.0">5850.0</temperature>
    <planet>
      <radius errorplus="0.14" errorminus="-0.09">0.96</radius>
      <semimajoraxis errorplus="0.0056" errorminus="-0.0056">0.1898</semimajoraxis>
      <discoverymethod>transit</discoverymethod>
      <name>K2-6 b</name>
      <lastupdate>2015-07-16</lastupdate>
      <period errorplus="0.0" errorminus="-0.0">30.9</period>
      <inclination/>
    </planet>
    <mass errorplus="0.07" errorminus="-0.07">0.97</mass>
  </star>
  <distance/>
  <declination>-1 11 54</declination>
  <rightascension>11 11 32</rightascension>
</system>

