<system>
  <star>
    <radius errorplus="0.01" errorminus="-0.01">0.72</radius>
    <mass errorplus="0.02" errorminus="-0.03">0.78</mass>
    <temperature errorplus="63.31" errorminus="-50.89">4708.0</temperature>
    <planet>
      <inclination/>
      <discoverymethod>transit</discoverymethod>
      <semimajoraxis/>
      <period errorplus="0.0" errorminus="-0.0">2.0</period>
      <radius errorplus="0.01" errorminus="-0.01">0.72</radius>
      <lastupdate>2016-05-10</lastupdate>
      <name>Kepler-1197 b</name>
    </planet>
    <name>Kepler-1197</name>
  </star>
  <distance errorplus="11.48" errorminus="-11.79">505.0</distance>
  <declination>42 35 26</declination>
  <rightascension>19 40 09</rightascension>
  <name>Kepler-1197</name>
</system>

