<system>
  <name>Kepler-909</name>
  <rightascension>19 30 22</rightascension>
  <declination>45 22 15</declination>
  <star>
    <name>Kepler-909</name>
    <radius errorplus="0.13" errorminus="-0.08">1.23</radius>
    <temperature errorplus="62.02" errorminus="-57.72">6154.0</temperature>
    <planet>
      <name>Kepler-909 b</name>
      <inclination/>
      <semimajoraxis/>
      <radius errorplus="0.13" errorminus="-0.08">1.23</radius>
      <lastupdate>2016-05-10</lastupdate>
      <period errorplus="0.0" errorminus="-0.0">13.9</period>
      <discoverymethod>transit</discoverymethod>
    </planet>
    <mass errorplus="0.04" errorminus="-0.04">1.17</mass>
  </star>
  <distance errorplus="33.11" errorminus="-22.67">318.0</distance>
</system>

