<system>
  <name>Kepler-182</name>
  <rightascension>19 49 48</rightascension>
  <star>
    <name>Kepler-182</name>
    <radius errorplus="0.51" errorminus="-0.51">1.15</radius>
    <mass>1.14</mass>
    <temperature errorplus="200.0" errorminus="-200.0">6250.0</temperature>
    <planet>
      <name>Kepler-182 c</name>
      <discoverymethod>transit</discoverymethod>
      <lastupdate>2014-05-14</lastupdate>
      <radius errorplus="0.51" errorminus="-0.51">1.15</radius>
      <semimajoraxis>0.157</semimajoraxis>
      <period errorplus="0.0" errorminus="-0.0">20.7</period>
      <inclination/>
    </planet>
    <planet>
      <name>Kepler-182 b</name>
      <discoverymethod>transit</discoverymethod>
      <lastupdate>2014-05-14</lastupdate>
      <radius errorplus="0.51" errorminus="-0.51">1.15</radius>
      <semimajoraxis>0.096</semimajoraxis>
      <period errorplus="0.0" errorminus="-0.0">9.8</period>
      <inclination/>
    </planet>
  </star>
  <distance/>
  <declination>50 35 10</declination>
</system>

