<system>
  <rightascension>19 42 30</rightascension>
  <distance errorminus="-167.88" errorplus="338.05">1126.0</distance>
  <name>Kepler-557</name>
  <star>
    <temperature errorminus="-199.33" errorplus="151.79">6068.0</temperature>
    <mass errorminus="-0.09" errorplus="0.12">1.11</mass>
    <name>Kepler-557</name>
    <planet>
      <period errorminus="-0.0" errorplus="0.0">3.7</period>
      <radius errorminus="-0.16" errorplus="0.35">1.16</radius>
      <discoverymethod>transit</discoverymethod>
      <inclination/>
      <name>Kepler-557 b</name>
      <lastupdate>2016-05-10</lastupdate>
      <semimajoraxis/>
    </planet>
    <radius errorminus="-0.16" errorplus="0.35">1.16</radius>
  </star>
  <declination>41 36 54</declination>
</system>

