<system>
  <rightascension>19 52 54</rightascension>
  <distance errorminus="-102.97" errorplus="206.21">979.0</distance>
  <name>Kepler-1041</name>
  <star>
    <temperature errorminus="-105.23" errorplus="107.73">5957.0</temperature>
    <mass errorminus="-0.07" errorplus="0.07">1.06</mass>
    <name>Kepler-1041</name>
    <planet>
      <period errorminus="-0.0" errorplus="0.0">24.8</period>
      <radius errorminus="-0.11" errorplus="0.23">1.08</radius>
      <discoverymethod>transit</discoverymethod>
      <inclination/>
      <name>Kepler-1041 b</name>
      <lastupdate>2016-05-10</lastupdate>
      <semimajoraxis/>
    </planet>
    <radius errorminus="-0.11" errorplus="0.23">1.08</radius>
  </star>
  <declination>49 40 59</declination>
</system>

