<system>
  <name>Kepler-861</name>
  <rightascension>19 21 14</rightascension>
  <declination>46 13 34</declination>
  <star>
    <name>Kepler-861</name>
    <mass errorplus="0.04" errorminus="-0.04">0.82</mass>
    <temperature errorplus="65.25" errorminus="-72.9">5047.0</temperature>
    <radius errorplus="0.04" errorminus="-0.04">0.78</radius>
    <planet>
      <inclination/>
      <radius errorplus="0.04" errorminus="-0.04">0.78</radius>
      <period errorplus="0.0" errorminus="-0.0">3.9</period>
      <name>Kepler-861 b</name>
      <lastupdate>2016-05-10</lastupdate>
      <discoverymethod>transit</discoverymethod>
      <semimajoraxis/>
    </planet>
  </star>
  <distance errorplus="40.31" errorminus="-41.15">806.0</distance>
</system>

