<system>
  <star>
    <planet>
      <radius errorplus="0.02" errorminus="-0.02">0.6</radius>
      <discoverymethod>transit</discoverymethod>
      <lastupdate>2015-01-06</lastupdate>
      <inclination errorplus="0.06" errorminus="-0.12">89.94</inclination>
      <period errorplus="0.0" errorminus="-0.0">112.3</period>
      <semimajoraxis errorplus="0.209" errorminus="-0.06">0.409</semimajoraxis>
      <name>Kepler-442 b</name>
      <eccentricity>0.04</eccentricity>
    </planet>
    <radius errorplus="0.02" errorminus="-0.02">0.6</radius>
    <temperature errorplus="100.0" errorminus="-100.0">4402.0</temperature>
    <mass errorplus="0.03" errorminus="-0.03">0.61</mass>
    <name>Kepler-442</name>
  </star>
  <distance errorplus="19.0" errorminus="-22.0">342.0</distance>
  <rightascension>19 21 59</rightascension>
  <declination>39 16 48</declination>
  <name>Kepler-442</name>
</system>

