<system><rightascension>19 57 41</rightascension><star><mass>0.89</mass><planet><inclination></inclination><period>4.7</period><radius>0.95</radius><discoverymethod>transit Timing Variations</discoverymethod><semimajoraxis></semimajoraxis><lastupdate>2014-05-28</lastupdate><name>Kepler-414 b</name></planet><planet><inclination></inclination><period>7.2</period><radius>0.95</radius><discoverymethod>transit Timing Variations</discoverymethod><semimajoraxis></semimajoraxis><lastupdate>2014-05-28</lastupdate><name>Kepler-414 c</name></planet><name>Kepler-414</name><radius>0.95</radius><temperature></temperature></star><distance></distance><name>Kepler-414</name><declination>48 14 39</declination></system>
