<system>
  <name>Kepler-273</name>
  <rightascension>19 18 07</rightascension>
  <declination>47 41 51</declination>
  <star>
    <name>Kepler-273</name>
    <mass/>
    <temperature errorplus="200.0" errorminus="-200.0">5626.0</temperature>
    <radius errorplus="0.46" errorminus="-0.46">0.81</radius>
    <planet>
      <inclination/>
      <radius errorplus="0.46" errorminus="-0.46">0.81</radius>
      <period errorplus="0.0" errorminus="-0.0">8.0</period>
      <name>Kepler-273 c</name>
      <lastupdate>2014-05-14</lastupdate>
      <discoverymethod>transit</discoverymethod>
      <semimajoraxis>0.073</semimajoraxis>
    </planet>
    <planet>
      <inclination/>
      <radius errorplus="0.46" errorminus="-0.46">0.81</radius>
      <period errorplus="0.0" errorminus="-0.0">2.9</period>
      <name>Kepler-273 b</name>
      <lastupdate>2014-05-14</lastupdate>
      <discoverymethod>transit</discoverymethod>
      <semimajoraxis>0.037</semimajoraxis>
    </planet>
  </star>
  <distance/>
</system>

