<system><distance errorplus="288.8" errorminus="-99.54">715.0</distance><declination>41 36 21</declination><star><planet><lastupdate>2016-05-10</lastupdate><radius errorplus="0.54" errorminus="-0.17">1.29</radius><name>Kepler-1288 b</name><semimajoraxis></semimajoraxis><discoverymethod>transit</discoverymethod><period errorplus="0.0" errorminus="-0.0">2.8</period><inclination></inclination></planet><mass errorplus="0.16" errorminus="-0.08">1.2</mass><radius errorplus="0.54" errorminus="-0.17">1.29</radius><temperature errorplus="87.95" errorminus="-135.79">6132.0</temperature><name>Kepler-1288</name></star><name>Kepler-1288</name><rightascension>19 42 48</rightascension></system>
