<system><distance errorplus="515.33" errorminus="-275.94">1413.0</distance><declination>43 29 35</declination><star><planet><lastupdate>2016-05-10</lastupdate><radius errorplus="0.67" errorminus="-0.35">1.81</radius><name>Kepler-644 b</name><semimajoraxis></semimajoraxis><discoverymethod>transit</discoverymethod><period errorplus="0.0" errorminus="-0.0">3.2</period><inclination></inclination></planet><mass errorplus="0.22" errorminus="-0.17">1.49</mass><radius errorplus="0.67" errorminus="-0.35">1.81</radius><temperature errorplus="156.03" errorminus="-238.58">6747.0</temperature><name>Kepler-644</name></star><name>Kepler-644</name><rightascension>19 28 32</rightascension></system>
