<system>
  <star>
    <radius errorplus="0.03" errorminus="-0.04">0.74</radius>
    <mass errorplus="0.04" errorminus="-0.04">0.77</mass>
    <temperature errorplus="84.63" errorminus="-57.56">4895.0</temperature>
    <planet>
      <inclination/>
      <discoverymethod>transit</discoverymethod>
      <semimajoraxis/>
      <period errorplus="0.0" errorminus="-0.0">13.6</period>
      <radius errorplus="0.03" errorminus="-0.04">0.74</radius>
      <lastupdate>2016-05-10</lastupdate>
      <name>Kepler-1242 b</name>
    </planet>
    <name>Kepler-1242</name>
  </star>
  <distance errorplus="29.42" errorminus="-37.12">682.0</distance>
  <declination>41 11 46</declination>
  <rightascension>18 36 22</rightascension>
  <name>Kepler-1242</name>
</system>

