<system>
  <name>Kepler-653</name>
  <distance errorplus="86.31" errorminus="-79.11">593.0</distance>
  <declination>46 43 04</declination>
  <rightascension>18 12 46</rightascension>
  <star>
    <temperature errorplus="54.97" errorminus="-60.88">5665.0</temperature>
    <name>Kepler-653</name>
    <mass errorplus="0.05" errorminus="-0.04">1.02</mass>
    <radius errorplus="0.17" errorminus="-0.16">1.19</radius>
    <planet>
      <name>Kepler-653 b</name>
      <semimajoraxis/>
      <radius errorplus="0.17" errorminus="-0.16">1.19</radius>
      <discoverymethod>transit</discoverymethod>
      <inclination/>
      <period errorplus="0.0" errorminus="-0.0">14.7</period>
      <lastupdate>2016-05-10</lastupdate>
    </planet>
    <planet>
      <name>Kepler-653 c</name>
      <semimajoraxis/>
      <radius errorplus="0.17" errorminus="-0.16">1.19</radius>
      <discoverymethod>transit</discoverymethod>
      <inclination/>
      <period errorplus="0.0" errorminus="-0.0">0.9</period>
      <lastupdate>2016-05-10</lastupdate>
    </planet>
  </star>
</system>

