<system>
  <star>
    <radius errorplus="0.42" errorminus="-0.42">0.89</radius>
    <mass/>
    <temperature errorplus="250.0" errorminus="-250.0">5818.0</temperature>
    <planet>
      <inclination/>
      <discoverymethod>transit</discoverymethod>
      <semimajoraxis>0.095</semimajoraxis>
      <period errorplus="0.0" errorminus="-0.0">10.6</period>
      <radius errorplus="0.42" errorminus="-0.42">0.89</radius>
      <lastupdate>2014-05-14</lastupdate>
      <name>Kepler-405 b</name>
    </planet>
    <planet>
      <inclination/>
      <discoverymethod>transit</discoverymethod>
      <semimajoraxis>0.188</semimajoraxis>
      <period errorplus="0.0" errorminus="-0.0">29.7</period>
      <radius errorplus="0.42" errorminus="-0.42">0.89</radius>
      <lastupdate>2014-05-14</lastupdate>
      <name>Kepler-405 c</name>
    </planet>
    <name>Kepler-405</name>
  </star>
  <distance/>
  <declination>38 20 24</declination>
  <rightascension>19 24 34</rightascension>
  <name>Kepler-405</name>
</system>

