<system>
  <name>Kepler-1063</name>
  <rightascension>19 31 36</rightascension>
  <declination>38 08 34</declination>
  <star>
    <name>Kepler-1063</name>
    <mass errorplus="0.11" errorminus="-0.07">1.09</mass>
    <temperature errorplus="188.84" errorminus="-155.38">5945.0</temperature>
    <radius errorplus="0.3" errorminus="-0.14">1.14</radius>
    <planet>
      <inclination/>
      <radius errorplus="0.3" errorminus="-0.14">1.14</radius>
      <period errorplus="0.0" errorminus="-0.0">14.1</period>
      <name>Kepler-1063 b</name>
      <lastupdate>2016-05-10</lastupdate>
      <discoverymethod>transit</discoverymethod>
      <semimajoraxis/>
    </planet>
  </star>
  <distance errorplus="95.13" errorminus="-48.81">365.0</distance>
</system>

