<system><distance errorplus="67.02" errorminus="-48.86">587.0</distance><declination>40 32 49</declination><star><planet><lastupdate>2016-05-10</lastupdate><radius errorplus="0.14" errorminus="-0.1">1.21</radius><name>Kepler-1276 b</name><semimajoraxis></semimajoraxis><discoverymethod>transit</discoverymethod><period errorplus="0.0" errorminus="-0.0">12.6</period><inclination></inclination></planet><mass errorplus="0.05" errorminus="-0.05">1.14</mass><radius errorplus="0.14" errorminus="-0.1">1.21</radius><temperature errorplus="65.25" errorminus="-55.24">6188.0</temperature><name>Kepler-1276</name></star><name>Kepler-1276</name><rightascension>19 51 25</rightascension></system>
