<system>
  <rightascension>19 08 58</rightascension>
  <distance errorminus="-161.97" errorplus="165.01">1020.0</distance>
  <name>Kepler-541</name>
  <star>
    <temperature errorminus="-99.75" errorplus="102.75">6166.0</temperature>
    <mass errorminus="-0.16" errorplus="0.12">1.41</mass>
    <name>Kepler-541</name>
    <planet>
      <period errorminus="-0.0" errorplus="0.0">5.1</period>
      <radius errorminus="-0.33" errorplus="0.32">2.06</radius>
      <discoverymethod>transit</discoverymethod>
      <inclination/>
      <name>Kepler-541 b</name>
      <lastupdate>2016-05-10</lastupdate>
      <semimajoraxis/>
    </planet>
    <radius errorminus="-0.33" errorplus="0.32">2.06</radius>
  </star>
  <declination>38 27 29</declination>
</system>

