<system>
  <distance/>
  <name>Kepler-304</name>
  <declination>40 33 27</declination>
  <star>
    <radius errorplus="0.04" errorminus="-0.04">0.69</radius>
    <temperature errorplus="100.0" errorminus="-100.0">4731.0</temperature>
    <name>Kepler-304</name>
    <mass>0.8</mass>
    <planet>
      <radius errorplus="0.04" errorminus="-0.04">0.69</radius>
      <semimajoraxis>0.08</semimajoraxis>
      <lastupdate>2014-05-14</lastupdate>
      <name>Kepler-304 d</name>
      <inclination/>
      <discoverymethod>transit</discoverymethod>
      <period errorplus="0.0" errorminus="-0.0">9.7</period>
    </planet>
    <planet>
      <radius errorplus="0.04" errorminus="-0.04">0.69</radius>
      <semimajoraxis>0.039</semimajoraxis>
      <lastupdate>2014-05-14</lastupdate>
      <name>Kepler-304 b</name>
      <inclination/>
      <discoverymethod>transit</discoverymethod>
      <period errorplus="0.0" errorminus="-0.0">3.3</period>
    </planet>
    <planet>
      <radius errorplus="0.04" errorminus="-0.04">0.69</radius>
      <semimajoraxis/>
      <lastupdate>2016-05-10</lastupdate>
      <name>Kepler-304 e</name>
      <inclination/>
      <discoverymethod>transit</discoverymethod>
      <period errorplus="0.0" errorminus="-0.0">1.5</period>
    </planet>
    <planet>
      <radius errorplus="0.04" errorminus="-0.04">0.69</radius>
      <semimajoraxis>0.054</semimajoraxis>
      <lastupdate>2014-05-14</lastupdate>
      <name>Kepler-304 c</name>
      <inclination/>
      <discoverymethod>transit</discoverymethod>
      <period errorplus="0.0" errorminus="-0.0">5.3</period>
    </planet>
  </star>
  <rightascension>19 26 30</rightascension>
</system>

