<system><rightascension>19 25 58</rightascension><star><mass errorminus="-0.07" errorplus="0.08">1.0</mass><planet><inclination></inclination><period errorminus="-0.0" errorplus="0.0">40.6</period><radius errorminus="-0.11" errorplus="0.21">1.0</radius><discoverymethod>transit</discoverymethod><semimajoraxis></semimajoraxis><lastupdate>2016-05-10</lastupdate><name>Kepler-581 b</name></planet><name>Kepler-581</name><radius errorminus="-0.11" errorplus="0.21">1.0</radius><temperature errorminus="-191.78" errorplus="199.71">5772.0</temperature></star><distance errorminus="-97.73" errorplus="178.61">833.0</distance><name>Kepler-581</name><declination>40 38 53</declination></system>
