<system>
  <name>Kepler-133</name>
  <distance/>
  <declination>48 19 13</declination>
  <rightascension>19 16 40</rightascension>
  <star>
    <temperature errorplus="100.0" errorminus="-100.0">5736.0</temperature>
    <name>Kepler-133</name>
    <mass/>
    <radius errorplus="0.24" errorminus="-0.24">1.43</radius>
    <planet>
      <name>Kepler-133 b</name>
      <semimajoraxis>0.083</semimajoraxis>
      <radius errorplus="0.24" errorminus="-0.24">1.43</radius>
      <discoverymethod>transit</discoverymethod>
      <inclination/>
      <period errorplus="0.0" errorminus="-0.0">8.1</period>
      <lastupdate>2014-05-14</lastupdate>
    </planet>
    <planet>
      <name>Kepler-133 c</name>
      <semimajoraxis>0.204</semimajoraxis>
      <radius errorplus="0.24" errorminus="-0.24">1.43</radius>
      <discoverymethod>transit</discoverymethod>
      <inclination/>
      <period errorplus="0.0" errorminus="-0.0">31.5</period>
      <lastupdate>2014-05-14</lastupdate>
    </planet>
  </star>
</system>

