<system>
  <star>
    <planet>
      <radius errorplus="0.31" errorminus="-0.14">1.12</radius>
      <discoverymethod>transit</discoverymethod>
      <lastupdate>2016-05-10</lastupdate>
      <inclination/>
      <period errorplus="0.0" errorminus="-0.0">36.3</period>
      <semimajoraxis/>
      <name>Kepler-1255 b</name>
    </planet>
    <radius errorplus="0.31" errorminus="-0.14">1.12</radius>
    <temperature errorplus="134.73" errorminus="-186.81">6018.0</temperature>
    <mass errorplus="0.1" errorminus="-0.09">1.08</mass>
    <name>Kepler-1255</name>
  </star>
  <distance errorplus="364.65" errorminus="-175.95">1344.0</distance>
  <rightascension>19 14 21</rightascension>
  <declination>42 43 35</declination>
  <name>Kepler-1255</name>
</system>

