<system>
  <rightascension>18 41 27</rightascension>
  <distance/>
  <name>Kepler-165</name>
  <star>
    <temperature errorminus="-200.0" errorplus="200.0">5211.0</temperature>
    <mass/>
    <name>Kepler-165</name>
    <planet>
      <period errorminus="-0.0" errorplus="0.0">15.3</period>
      <radius errorminus="-0.47" errorplus="0.47">0.77</radius>
      <discoverymethod>transit</discoverymethod>
      <inclination/>
      <name>Kepler-165 c</name>
      <lastupdate>2014-05-14</lastupdate>
      <semimajoraxis>0.11</semimajoraxis>
    </planet>
    <planet>
      <period errorminus="-0.0" errorplus="0.0">8.2</period>
      <radius errorminus="-0.47" errorplus="0.47">0.77</radius>
      <discoverymethod>transit</discoverymethod>
      <inclination/>
      <name>Kepler-165 b</name>
      <lastupdate>2014-05-14</lastupdate>
      <semimajoraxis>0.072</semimajoraxis>
    </planet>
    <radius errorminus="-0.47" errorplus="0.47">0.77</radius>
  </star>
  <declination>47 48 35</declination>
</system>

