<system>
  <name>Kepler-990</name>
  <rightascension>19 56 17</rightascension>
  <distance errorplus="242.95" errorminus="-130.03">933.0</distance>
  <star>
    <name>Kepler-990</name>
    <temperature errorplus="211.07" errorminus="-213.6">5948.0</temperature>
    <mass errorplus="0.12" errorminus="-0.09">1.05</mass>
    <planet>
      <name>Kepler-990 c</name>
      <period errorplus="0.0" errorminus="-0.0">0.5</period>
      <semimajoraxis/>
      <radius errorplus="0.27" errorminus="-0.14">1.08</radius>
      <lastupdate>2016-05-10</lastupdate>
      <inclination/>
      <discoverymethod>transit</discoverymethod>
    </planet>
    <planet>
      <name>Kepler-990 b</name>
      <period errorplus="0.0" errorminus="-0.0">9.9</period>
      <semimajoraxis/>
      <radius errorplus="0.27" errorminus="-0.14">1.08</radius>
      <lastupdate>2016-05-10</lastupdate>
      <inclination/>
      <discoverymethod>transit</discoverymethod>
    </planet>
    <radius errorplus="0.27" errorminus="-0.14">1.08</radius>
  </star>
  <declination>46 52 53</declination>
</system>

