<system>
  <name>Kepler-389</name>
  <rightascension>19 57 36</rightascension>
  <declination>44 54 00</declination>
  <star>
    <name>Kepler-389</name>
    <radius errorplus="0.4" errorminus="-0.4">0.79</radius>
    <temperature errorplus="250.0" errorminus="-250.0">5376.0</temperature>
    <planet>
      <name>Kepler-389 c</name>
      <inclination/>
      <semimajoraxis>0.11</semimajoraxis>
      <radius errorplus="0.4" errorminus="-0.4">0.79</radius>
      <lastupdate>2014-05-14</lastupdate>
      <period errorplus="0.0" errorminus="-0.0">14.5</period>
      <discoverymethod>transit</discoverymethod>
    </planet>
    <planet>
      <name>Kepler-389 b</name>
      <inclination/>
      <semimajoraxis>0.041</semimajoraxis>
      <radius errorplus="0.4" errorminus="-0.4">0.79</radius>
      <lastupdate>2014-05-14</lastupdate>
      <period errorplus="0.0" errorminus="-0.0">3.2</period>
      <discoverymethod>transit</discoverymethod>
    </planet>
    <mass>0.78</mass>
  </star>
  <distance/>
</system>

