<system>
  <name>Kepler-221</name>
  <distance/>
  <declination>46 50 06</declination>
  <rightascension>19 39 17</rightascension>
  <star>
    <temperature errorplus="100.0" errorminus="-100.0">5243.0</temperature>
    <name>Kepler-221</name>
    <mass>0.72</mass>
    <radius errorplus="0.07" errorminus="-0.07">0.82</radius>
    <planet>
      <name>Kepler-221 c</name>
      <semimajoraxis>0.059</semimajoraxis>
      <radius errorplus="0.07" errorminus="-0.07">0.82</radius>
      <discoverymethod>transit</discoverymethod>
      <inclination/>
      <period errorplus="0.0" errorminus="-0.0">5.7</period>
      <lastupdate>2014-05-14</lastupdate>
    </planet>
    <planet>
      <name>Kepler-221 b</name>
      <semimajoraxis>0.037</semimajoraxis>
      <radius errorplus="0.07" errorminus="-0.07">0.82</radius>
      <discoverymethod>transit</discoverymethod>
      <inclination/>
      <period errorplus="0.0" errorminus="-0.0">2.8</period>
      <lastupdate>2014-05-14</lastupdate>
    </planet>
    <planet>
      <name>Kepler-221 d</name>
      <semimajoraxis>0.087</semimajoraxis>
      <radius errorplus="0.07" errorminus="-0.07">0.82</radius>
      <discoverymethod>transit</discoverymethod>
      <inclination/>
      <period errorplus="0.0" errorminus="-0.0">10.0</period>
      <lastupdate>2014-05-14</lastupdate>
    </planet>
    <planet>
      <name>Kepler-221 e</name>
      <semimajoraxis>0.13</semimajoraxis>
      <radius errorplus="0.07" errorminus="-0.07">0.82</radius>
      <discoverymethod>transit</discoverymethod>
      <inclination/>
      <period errorplus="0.0" errorminus="-0.0">18.4</period>
      <lastupdate>2014-05-14</lastupdate>
    </planet>
  </star>
</system>

