<system>
  <name>Kepler-615</name>
  <rightascension>18 27 02</rightascension>
  <declination>46 19 17</declination>
  <star>
    <name>Kepler-615</name>
    <mass errorplus="0.04" errorminus="-0.04">0.73</mass>
    <temperature errorplus="41.24" errorminus="-43.29">4655.0</temperature>
    <radius errorplus="0.03" errorminus="-0.04">0.69</radius>
    <planet>
      <inclination/>
      <radius errorplus="0.03" errorminus="-0.04">0.69</radius>
      <period errorplus="0.0" errorminus="-0.0">10.4</period>
      <name>Kepler-615 b</name>
      <lastupdate>2016-05-10</lastupdate>
      <discoverymethod>transit</discoverymethod>
      <semimajoraxis/>
    </planet>
  </star>
  <distance errorplus="14.56" errorminus="-19.99">330.0</distance>
</system>

