<system>
  <name>Kepler-678</name>
  <rightascension>19 27 19</rightascension>
  <distance errorplus="112.58" errorminus="-61.05">875.0</distance>
  <star>
    <name>Kepler-678</name>
    <temperature errorplus="72.95" errorminus="-108.11">5520.0</temperature>
    <mass errorplus="0.04" errorminus="-0.05">0.94</mass>
    <planet>
      <name>Kepler-678 b</name>
      <period errorplus="0.0" errorminus="-0.0">7.3</period>
      <semimajoraxis/>
      <radius errorplus="0.12" errorminus="-0.06">0.91</radius>
      <lastupdate>2016-05-10</lastupdate>
      <inclination/>
      <discoverymethod>transit</discoverymethod>
    </planet>
    <radius errorplus="0.12" errorminus="-0.06">0.91</radius>
  </star>
  <declination>50 29 40</declination>
</system>

