<system><rightascension>19 42 56</rightascension><star><mass errorminus="-0.11" errorplus="0.01">1.28</mass><planet><inclination></inclination><period errorminus="-0.0" errorplus="0.0">6.0</period><radius errorminus="-0.41" errorplus="0.3">3.38</radius><discoverymethod>transit</discoverymethod><semimajoraxis></semimajoraxis><lastupdate>2016-05-10</lastupdate><name>Kepler-1270 b</name></planet><name>Kepler-1270</name><radius errorminus="-0.41" errorplus="0.3">3.38</radius><temperature errorminus="-34.17" errorplus="40.17">5047.0</temperature></star><distance errorminus="-145.11" errorplus="110.86">1204.0</distance><name>Kepler-1270</name><declination>48 38 43</declination></system>
